{
  "country": "AZ",
  "name": "Azerbaijan",
  "sources": [
    {
      "id": "az-earthquake-usgs-bbox",
      "authority": "US Geological Survey (USGS)",
      "coverage": {
        "countries": [
          "AZ"
        ]
      },
      "capability": "earthquake",
      "outputModel": "risk-event",
      "access": "public",
      "format": "geojson",
      "endpoint": "https://earthquake.usgs.gov/fdsnws/event/1/query?format=geojson&limit=100&minlatitude=38.3&maxlatitude=41.9&minlongitude=44.4&maxlongitude=50.5",
      "refreshSeconds": 300,
      "proxyRequired": false,
      "attribution": "US Geological Survey",
      "termsUrl": "https://earthquake.usgs.gov/earthquakes/feed/terms.php",
      "status": "discovered",
      "notes": "Confirmed HTTP 200 application/json (GeoJSON). FDSN event query bounded to Azerbaijan's bounding box; primary international fallback for Azerbaijani seismicity (South Caspian is highly active)."
    },
    {
      "id": "az-earthquake-emsc-bbox",
      "authority": "EMSC / European-Mediterranean Seismological Centre",
      "coverage": {
        "countries": [
          "AZ"
        ]
      },
      "capability": "earthquake",
      "outputModel": "risk-event",
      "access": "public",
      "format": "json",
      "endpoint": "https://www.seismicportal.eu/fdsnws/event/1/query?format=json&limit=50&minlat=38.3&maxlat=41.9&minlon=44.4&maxlon=50.5",
      "refreshSeconds": 300,
      "proxyRequired": false,
      "attribution": "EMSC-CSEM",
      "termsUrl": "https://www.seismicportal.eu/",
      "status": "discovered",
      "notes": "Confirmed HTTP 200 application/json (with limit=50; wider bbox returns 413). FDSN event query bounded to Azerbaijan's bounding box; secondary European fallback feed."
    },
    {
      "id": "az-weather-open-meteo",
      "authority": "Open-Meteo",
      "coverage": {
        "countries": [
          "AZ"
        ]
      },
      "capability": "road-weather",
      "outputModel": "supplemental-signal",
      "access": "public",
      "format": "json",
      "endpoint": "https://api.open-meteo.com/v1/forecast?latitude=40.41&longitude=49.87&current=temperature_2m,relative_humidity_2m,wind_speed_10m,weather_code&daily=weather_code,temperature_2m_max&forecast_days=3",
      "refreshSeconds": 1800,
      "proxyRequired": false,
      "attribution": "Open-Meteo (CC BY 4.0)",
      "termsUrl": "https://open-meteo.com/en/docs",
      "status": "discovered",
      "notes": "Confirmed HTTP 200 application/json. Point forecast for Baku; weather_code + temperature/humidity/wind act as a fire-weather and severe-weather signal. Azerbaijan is not a Meteoalarm member, so Open-Meteo is the verifiable weather source. Repeat per city as needed."
    },
    {
      "id": "az-air-quality-open-meteo",
      "authority": "Open-Meteo (CAMs)",
      "coverage": {
        "countries": [
          "AZ"
        ]
      },
      "capability": "environmental-health",
      "outputModel": "supplemental-signal",
      "access": "public",
      "format": "json",
      "endpoint": "https://air-quality-api.open-meteo.com/v1/air-quality?latitude=40.41&longitude=49.87&current=european_aqi,pm10,pm2_5,ozone&forecast_days=1",
      "refreshSeconds": 3600,
      "proxyRequired": false,
      "attribution": "Open-Meteo / Copernicus Atmosphere Monitoring Service",
      "termsUrl": "https://open-meteo.com/en/docs/air-quality-api",
      "status": "discovered",
      "notes": "Confirmed HTTP 200 application/json. European AQI and pollutant levels for Baku; usable as an environmental-health signal across Azerbaijan."
    },
    {
      "id": "az-flood-open-meteo",
      "authority": "Open-Meteo (GloFAS)",
      "coverage": {
        "countries": [
          "AZ"
        ]
      },
      "capability": "water",
      "outputModel": "supplemental-signal",
      "access": "public",
      "format": "json",
      "endpoint": "https://flood-api.open-meteo.com/v1/flood?latitude=40.41&longitude=49.87&current=river_discharge,river_discharge_max&forecast_days=3",
      "refreshSeconds": 3600,
      "proxyRequired": false,
      "attribution": "Open-Meteo / Copernicus GloFAS",
      "termsUrl": "https://open-meteo.com/en/docs/flood-api",
      "status": "discovered",
      "notes": "Confirmed HTTP 200 application/json. River discharge / flood-layer forecast; usable as a flood signal for Azerbaijani river basins (e.g. Kura, Araz)."
    },
    {
      "id": "az-marine-open-meteo",
      "authority": "Open-Meteo (ECMWF/GFS waves)",
      "coverage": {
        "countries": [
          "AZ"
        ]
      },
      "capability": "marine",
      "outputModel": "supplemental-signal",
      "access": "public",
      "format": "json",
      "endpoint": "https://marine-api.open-meteo.com/v1/marine?latitude=40.3&longitude=50.3&current=wave_height,wave_direction,wind_wave_height&forecast_days=1",
      "refreshSeconds": 3600,
      "proxyRequired": false,
      "attribution": "Open-Meteo",
      "termsUrl": "https://open-meteo.com/en/docs/marine-weather-api",
      "status": "discovered",
      "notes": "Confirmed HTTP 200 application/json. Caspian Sea coastal marine forecast (wave height) off the Azerbaijani coast near Baku; relevant for coastal/marine risk."
    },
    {
      "id": "az-wildfire-nasa-firms",
      "authority": "NASA FIRMS (Fire Information for Resource Management System)",
      "coverage": {
        "countries": [
          "AZ"
        ]
      },
      "capability": "wildfire",
      "outputModel": "map-overlay",
      "access": "api-key",
      "format": "csv",
      "endpoint": "https://firms.modaps.eosdis.nasa.gov/api/area/csv/INSERT_MAP_KEY/VIIRS_SNPP_NRT/44.4,38.3,50.5,41.9/1",
      "refreshSeconds": 3600,
      "proxyRequired": false,
      "attribution": "NASA FIRMS / USGS",
      "termsUrl": "https://firms.modaps.eosdis.nasa.gov/api/area/",
      "status": "discovered",
      "notes": "Confirmed HTTP 400 text/plain without a MAP_KEY (api key required). VIIRS S-NPP NRT active fire area extract bounded to Azerbaijan's bounding box; replace INSERT_MAP_KEY with a valid NASA FIRMS MAP_KEY."
    },
    {
      "id": "az-grid-eia",
      "authority": "US Energy Information Administration (EIA) — international electricity",
      "coverage": {
        "countries": [
          "AZ"
        ]
      },
      "capability": "grid",
      "outputModel": "supplemental-signal",
      "access": "api-key",
      "format": "json",
      "endpoint": "https://api.eia.gov/v2/international/data/?frequency=monthly&data[0]=value&facets[countryId][]=AZE&api_key=YOUR_EIA_KEY",
      "refreshSeconds": 86400,
      "proxyRequired": false,
      "attribution": "U.S. Energy Information Administration",
      "termsUrl": "https://www.eia.gov/terms/",
      "status": "discovered",
      "notes": "EIA international electricity/data API supports Azerbaijan (countryId AZE) with an api_key parameter; key required (endpoint returns no data without a valid key)."
    }
  ]
}
