{
  "country": "NG",
  "name": "Nigeria",
  "sources": [
    {
      "id": "ng-earthquake-emsc",
      "authority": "EMSC / European-Mediterranean Seismological Centre",
      "coverage": { "countries": ["NG"] },
      "capability": "earthquake",
      "outputModel": "risk-event",
      "access": "public",
      "format": "json",
      "endpoint": "https://www.seismicportal.eu/fdsnws/event/1/query?format=json&minlat=4.0&maxlat=14.0&minlon=2.0&maxlon=15.0",
      "refreshSeconds": 600,
      "proxyRequired": false,
      "attribution": "EMSC",
      "termsUrl": "https://www.seismicportal.eu/terms_of_use.html",
      "status": "discovered",
      "notes": "EMSC FDSNWS event query constrained to Nigeria bbox. Confirmed 200 application/json."
    },
    {
      "id": "ng-earthquake-usgs",
      "authority": "USGS Earthquake Hazards Program",
      "coverage": { "countries": ["NG"] },
      "capability": "earthquake",
      "outputModel": "risk-event",
      "access": "public",
      "format": "geojson",
      "endpoint": "https://earthquake.usgs.gov/fdsnws/event/1/query?format=geojson&minlatitude=4.0&maxlatitude=14.0&minlongitude=2.0&maxlongitude=15.0",
      "refreshSeconds": 600,
      "proxyRequired": false,
      "attribution": "USGS",
      "termsUrl": "https://earthquake.usgs.gov/help/terms.php",
      "status": "discovered",
      "notes": "USGS FDSNWS GeoJSON event feed for Nigeria bbox. Confirmed 200 application/json."
    },
    {
      "id": "ng-weather-openmeteo",
      "authority": "Open-Meteo",
      "coverage": { "countries": ["NG"] },
      "capability": "environmental-health",
      "outputModel": "supplemental-signal",
      "access": "public",
      "format": "json",
      "endpoint": "https://api.open-meteo.com/v1/forecast?latitude=9.1&longitude=7.4&current=temperature_2m,relative_humidity_2m,precipitation,wind_speed_10m,weather_code",
      "refreshSeconds": 900,
      "proxyRequired": false,
      "attribution": "Open-Meteo",
      "termsUrl": "https://open-meteo.com/en/docs",
      "status": "discovered",
      "notes": "Open-Meteo forecast cross-check for Nigeria (Abuja). Confirmed 200 application/json."
    },
    {
      "id": "ng-airquality-openmeteo",
      "authority": "Open-Meteo Air Quality",
      "coverage": { "countries": ["NG"] },
      "capability": "environmental-health",
      "outputModel": "supplemental-signal",
      "access": "public",
      "format": "json",
      "endpoint": "https://air-quality-api.open-meteo.com/v1/air-quality?latitude=9.1&longitude=7.4&current=pm2_5,pm10,ozone,us_aqi",
      "refreshSeconds": 3600,
      "proxyRequired": false,
      "attribution": "Open-Meteo",
      "termsUrl": "https://open-meteo.com/en/docs/air-quality-api",
      "status": "discovered",
      "notes": "Open-Meteo air quality (PM2.5/PM10/O3/AQI) for Nigeria. Confirmed 200 application/json."
    },
    {
      "id": "ng-flood-openmeteo",
      "authority": "Open-Meteo Flood / Global Flood API",
      "coverage": { "countries": ["NG"] },
      "capability": "water",
      "outputModel": "supplemental-signal",
      "access": "public",
      "format": "json",
      "endpoint": "https://flood-api.open-meteo.com/v1/flood?latitude=9.1&longitude=7.4&daily=river_discharge",
      "refreshSeconds": 3600,
      "proxyRequired": false,
      "attribution": "Open-Meteo",
      "termsUrl": "https://open-meteo.com/en/docs/flood-api",
      "status": "discovered",
      "notes": "Open-Meteo flood/river-discharge API for Nigeria. Confirmed 200 application/json."
    },
    {
      "id": "ng-marine-openmeteo",
      "authority": "Open-Meteo Marine",
      "coverage": { "countries": ["NG"] },
      "capability": "marine",
      "outputModel": "supplemental-signal",
      "access": "public",
      "format": "json",
      "endpoint": "https://marine-api.open-meteo.com/v1/marine?latitude=9.1&longitude=7.4&current=wave_height,wave_period,wind_wave_height",
      "refreshSeconds": 3600,
      "proxyRequired": false,
      "attribution": "Open-Meteo",
      "termsUrl": "https://open-meteo.com/en/docs/marine-weather-api",
      "status": "discovered",
      "notes": "Open-Meteo marine (wave height/period) for Nigeria coastal waters. Confirmed 200 application/json. Coastal state."
    },
    {
      "id": "ng-wildfire-firms",
      "authority": "NASA FIRMS",
      "coverage": { "countries": ["NG"] },
      "capability": "wildfire",
      "outputModel": "map-overlay",
      "access": "api-key",
      "format": "csv",
      "endpoint": "https://firms.modaps.eosdis.nasa.gov/api/area/csv/MAP_KEY/VIIRS_SNPP_NRT/4.0,2.0,14.0,15.0/1",
      "refreshSeconds": 3600,
      "proxyRequired": true,
      "attribution": "NASA FIRMS",
      "termsUrl": "https://firms.modaps.eosdis.nasa.gov/api/map_key/",
      "status": "discovered",
      "notes": "NASA FIRMS area API for Nigeria bbox. Returns 400 without MAP_KEY (confirmed). Requires API key."
    },
    {
      "id": "ng-observations-nimet-wis2",
      "authority": "Nigerian Meteorological Agency (NiMet) — WIS2",
      "coverage": { "countries": ["NG"] },
      "capability": "environmental-health",
      "outputModel": "supplemental-signal",
      "access": "public",
      "format": "geojson",
      "endpoint": "https://wis2.nimet.gov.ng/oapi/collections/urn:wmo:md:ng-nimet:surface-based-observations.synop/items",
      "refreshSeconds": 1800,
      "proxyRequired": false,
      "attribution": "NiMet (WMO WIS2)",
      "termsUrl": "https://wis2.nimet.gov.ng/",
      "status": "discovered",
      "notes": "NiMet WIS2 OAPI GeoJSON SYNOP surface observations (FeatureCollection). Confirmed 200 application/json. National meteorological observations feed."
    },
    {
      "id": "ng-grid-eia",
      "authority": "U.S. Energy Information Administration",
      "coverage": { "countries": ["NG"] },
      "capability": "grid",
      "outputModel": "supplemental-signal",
      "access": "api-key",
      "format": "json",
      "endpoint": "https://api.eia.gov/v2/international/data/?api_key=MAP_KEY",
      "refreshSeconds": 86400,
      "proxyRequired": true,
      "attribution": "EIA",
      "termsUrl": "https://www.eia.gov/terms/",
      "status": "discovered",
      "notes": "EIA international electricity/energy data for Nigeria. Returns 403 without key (confirmed). Requires API key."
    }
  ]
}
